{"version":3,"kind":"Article","sha256":"f68e8f7f63349baf1b7201bd9d08c70ede0f4421199ef996faf7a21610f0ee01","slug":"acronyms","location":"/appendices/acronyms.md","dependencies":[],"frontmatter":{"title":"Acronyms","content_includes_title":false,"github":"https://github.com/ua-asf/nisar-docs","numbering":{"figure":{"enabled":true,"continue":true},"title":{"offset":1}},"abbreviations":{"AWS":"Amazon Web Services","DAAC":"Distributed Active Archive Center","DEM":"Digital Elevation Model","EDC":"Earthdata Cloud","ESDIS":"Earth Science Data and Information System","GCOV":"Geocoded Polarimetric Covariance","GOFF":"Geocoded Pixel Offsets","GSLC":"Geocoded Single Look Complex","GUNW":"Geocoded Unwrapped Interferogram","NISAR":"NASA-ISRO Synthetic Aperture Radar","NRB":"Normalized Radar Backscatter","RTC":"Radiometric Terrain Correction; Radiometrically Terrain-Corrected","SAR":"Synthetic Aperture Radar","UTM":"Universal Transverse Mercator","RIFG":"Range Doppler Wrapped Interferogram","ROFF":"Range Doppler Pixel Offsets","RRSD":"Radar Raw Signal Data","RSLC":"Range Doppler Single Look Complex","RUNW":"Range Doppler Unwrapped Interferogram"},"source_url":"https://github.com/ua-asf/nisar-docs/blob/main/appendices/acronyms.md","edit_url":"https://github.com/ua-asf/nisar-docs/edit/main/appendices/acronyms.md","exports":[{"format":"md","filename":"acronyms.md","url":"/acronyms-d21e57ed253b857bec7100b01fc5fcf0.md"}]},"mdast":{"type":"root","children":[{"type":"block","children":[{"type":"table","position":{"start":{"line":3,"column":1},"end":{"line":89,"column":1}},"children":[{"type":"tableRow","position":{"start":{"line":3,"column":1},"end":{"line":3,"column":1}},"children":[{"type":"tableCell","header":true,"align":"left","position":{"start":{"line":3,"column":1},"end":{"line":3,"column":1}},"children":[{"type":"strong","position":{"start":{"line":3,"column":1},"end":{"line":3,"column":1}},"children":[{"type":"text","value":"Acronym","position":{"start":{"line":3,"column":1},"end":{"line":3,"column":1}},"key":"M8MnNgceIR"}],"key":"WdPPLPIEkv"}],"key":"oH3i2bQLJI"},{"type":"tableCell","header":true,"align":"left","position":{"start":{"line":3,"column":1},"end":{"line":3,"column":1}},"children":[{"type":"strong","position":{"start":{"line":3,"column":1},"end":{"line":3,"column":1}},"children":[{"type":"text","value":"Definition","position":{"start":{"line":3,"column":1},"end":{"line":3,"column":1}},"key":"Gh05drIz28"}],"key":"JuNJQOViQZ"}],"key":"aYAv16wufx"}],"key":"b40pT2TzRS"},{"type":"tableRow","position":{"start":{"line":5,"column":1},"end":{"line":5,"column":1}},"children":[{"type":"tableCell","align":"left","position":{"start":{"line":5,"column":1},"end":{"line":5,"column":1}},"children":[{"type":"text","value":"ADT","position":{"start":{"line":5,"column":1},"end":{"line":5,"column":1}},"key":"l3oPmrkW2k"}],"key":"V3NHqbPk5W"},{"type":"tableCell","align":"left","position":{"start":{"line":5,"column":1},"end":{"line":5,"column":1}},"children":[{"type":"text","value":"Algorithm Development Team","position":{"start":{"line":5,"column":1},"end":{"line":5,"column":1}},"key":"LEB2BDufC2"}],"key":"ZEKVj2SBFD"}],"key":"paHoVtVWU1"},{"type":"tableRow","position":{"start":{"line":6,"column":1},"end":{"line":6,"column":1}},"children":[{"type":"tableCell","align":"left","position":{"start":{"line":6,"column":1},"end":{"line":6,"column":1}},"children":[{"type":"text","value":"AT","position":{"start":{"line":6,"column":1},"end":{"line":6,"column":1}},"key":"BC93IZIvWJ"}],"key":"iTaV5BDb44"},{"type":"tableCell","align":"left","position":{"start":{"line":6,"column":1},"end":{"line":6,"column":1}},"children":[{"type":"text","value":"Along Track","position":{"start":{"line":6,"column":1},"end":{"line":6,"column":1}},"key":"Vp8rChq4vQ"}],"key":"whKFnq6ks3"}],"key":"G0xOyvM2yM"},{"type":"tableRow","position":{"start":{"line":7,"column":1},"end":{"line":7,"column":1}},"children":[{"type":"tableCell","align":"left","position":{"start":{"line":7,"column":1},"end":{"line":7,"column":1}},"children":[{"type":"abbreviation","title":"Amazon Web Services","children":[{"type":"text","value":"AWS","key":"ghDikDdWPp"}],"key":"ie83mHP8kP"}],"key":"Xxn1iftpVO"},{"type":"tableCell","align":"left","position":{"start":{"line":7,"column":1},"end":{"line":7,"column":1}},"children":[{"type":"text","value":"Amazon Web Services","position":{"start":{"line":7,"column":1},"end":{"line":7,"column":1}},"key":"lILaIY8o47"}],"key":"uvuEVPUFW3"}],"key":"phTIHM3uck"},{"type":"tableRow","position":{"start":{"line":8,"column":1},"end":{"line":8,"column":1}},"children":[{"type":"tableCell","align":"left","position":{"start":{"line":8,"column":1},"end":{"line":8,"column":1}},"children":[{"type":"text","value":"BFPQ","position":{"start":{"line":8,"column":1},"end":{"line":8,"column":1}},"key":"G1kAab2dTO"}],"key":"IvRuA278aE"},{"type":"tableCell","align":"left","position":{"start":{"line":8,"column":1},"end":{"line":8,"column":1}},"children":[{"type":"text","value":"Block adaptive Floating-Point Quantization","position":{"start":{"line":8,"column":1},"end":{"line":8,"column":1}},"key":"p0dN0JG50m"}],"key":"lIIbZs55EX"}],"key":"YB4Nf53JUv"},{"type":"tableRow","position":{"start":{"line":9,"column":1},"end":{"line":9,"column":1}},"children":[{"type":"tableCell","align":"left","position":{"start":{"line":9,"column":1},"end":{"line":9,"column":1}},"children":[{"type":"text","value":"Cal/Val","position":{"start":{"line":9,"column":1},"end":{"line":9,"column":1}},"key":"WlIXSXiWxK"}],"key":"JP8tIqBTqY"},{"type":"tableCell","align":"left","position":{"start":{"line":9,"column":1},"end":{"line":9,"column":1}},"children":[{"type":"text","value":"Calibration and Validation (also sometimes cal/val)","position":{"start":{"line":9,"column":1},"end":{"line":9,"column":1}},"key":"fj7GBedKQJ"}],"key":"v5p9RrWRnh"}],"key":"zaUHCUkehv"},{"type":"tableRow","position":{"start":{"line":10,"column":1},"end":{"line":10,"column":1}},"children":[{"type":"tableCell","align":"left","position":{"start":{"line":10,"column":1},"end":{"line":10,"column":1}},"children":[{"type":"text","value":"CDR","position":{"start":{"line":10,"column":1},"end":{"line":10,"column":1}},"key":"qPMF0YE6ld"}],"key":"UBDoOePCzq"},{"type":"tableCell","align":"left","position":{"start":{"line":10,"column":1},"end":{"line":10,"column":1}},"children":[{"type":"text","value":"Critical Design Review","position":{"start":{"line":10,"column":1},"end":{"line":10,"column":1}},"key":"cm6fZaaZSd"}],"key":"iAqUgRgrcu"}],"key":"fYXA2EqFZs"},{"type":"tableRow","position":{"start":{"line":11,"column":1},"end":{"line":11,"column":1}},"children":[{"type":"tableCell","align":"left","position":{"start":{"line":11,"column":1},"end":{"line":11,"column":1}},"children":[{"type":"text","value":"CF","position":{"start":{"line":11,"column":1},"end":{"line":11,"column":1}},"key":"yKb1fDOs5n"}],"key":"xkBlI2XFlF"},{"type":"tableCell","align":"left","position":{"start":{"line":11,"column":1},"end":{"line":11,"column":1}},"children":[{"type":"text","value":"Climate and Forecast","position":{"start":{"line":11,"column":1},"end":{"line":11,"column":1}},"key":"ZmAkU4glSx"}],"key":"j7X1uJ2SfL"}],"key":"ULInyTVFDA"},{"type":"tableRow","position":{"start":{"line":12,"column":1},"end":{"line":12,"column":1}},"children":[{"type":"tableCell","align":"left","position":{"start":{"line":12,"column":1},"end":{"line":12,"column":1}},"children":[{"type":"text","value":"CPU","position":{"start":{"line":12,"column":1},"end":{"line":12,"column":1}},"key":"ivQPRHAASx"}],"key":"AULmJhxbjS"},{"type":"tableCell","align":"left","position":{"start":{"line":12,"column":1},"end":{"line":12,"column":1}},"children":[{"type":"text","value":"Central Processing Unit","position":{"start":{"line":12,"column":1},"end":{"line":12,"column":1}},"key":"gRH1Wm4O86"}],"key":"F3pua9EQki"}],"key":"PUu7clJh8M"},{"type":"tableRow","position":{"start":{"line":13,"column":1},"end":{"line":13,"column":1}},"children":[{"type":"tableCell","align":"left","position":{"start":{"line":13,"column":1},"end":{"line":13,"column":1}},"children":[{"type":"text","value":"CRSD","position":{"start":{"line":13,"column":1},"end":{"line":13,"column":1}},"key":"scjBjGEnYv"}],"key":"PW4qAyBZLU"},{"type":"tableCell","align":"left","position":{"start":{"line":13,"column":1},"end":{"line":13,"column":1}},"children":[{"type":"text","value":"Calibration Raw Signal Data","position":{"start":{"line":13,"column":1},"end":{"line":13,"column":1}},"key":"Sra4vTOYW2"}],"key":"gnA036ttvV"}],"key":"dCP0erDeom"},{"type":"tableRow","position":{"start":{"line":14,"column":1},"end":{"line":14,"column":1}},"children":[{"type":"tableCell","align":"left","position":{"start":{"line":14,"column":1},"end":{"line":14,"column":1}},"children":[{"type":"text","value":"CSV","position":{"start":{"line":14,"column":1},"end":{"line":14,"column":1}},"key":"J0T9cmMTiz"}],"key":"WxPaZTTLGi"},{"type":"tableCell","align":"left","position":{"start":{"line":14,"column":1},"end":{"line":14,"column":1}},"children":[{"type":"text","value":"Comma-separated values","position":{"start":{"line":14,"column":1},"end":{"line":14,"column":1}},"key":"XM5quPmRnB"}],"key":"isYTwiY3HO"}],"key":"xiXDIhajtB"},{"type":"tableRow","position":{"start":{"line":15,"column":1},"end":{"line":15,"column":1}},"children":[{"type":"tableCell","align":"left","position":{"start":{"line":15,"column":1},"end":{"line":15,"column":1}},"children":[{"type":"abbreviation","title":"Distributed Active Archive Center","children":[{"type":"text","value":"DAAC","key":"yt0kTsWcKo"}],"key":"W0O9imIjmG"}],"key":"mBSjrSMAKe"},{"type":"tableCell","align":"left","position":{"start":{"line":15,"column":1},"end":{"line":15,"column":1}},"children":[{"type":"text","value":"Distributed Active Archive Center","position":{"start":{"line":15,"column":1},"end":{"line":15,"column":1}},"key":"b17CQoJzyF"}],"key":"id4H0skJqx"}],"key":"hvUhKbqXLa"},{"type":"tableRow","position":{"start":{"line":16,"column":1},"end":{"line":16,"column":1}},"children":[{"type":"tableCell","align":"left","position":{"start":{"line":16,"column":1},"end":{"line":16,"column":1}},"children":[{"type":"abbreviation","title":"Digital Elevation Model","children":[{"type":"text","value":"DEM","key":"u5q27jELA9"}],"key":"b02byAiNrB"}],"key":"ld079xWLEP"},{"type":"tableCell","align":"left","position":{"start":{"line":16,"column":1},"end":{"line":16,"column":1}},"children":[{"type":"text","value":"Digital Elevation Model","position":{"start":{"line":16,"column":1},"end":{"line":16,"column":1}},"key":"UVBQepSM4j"}],"key":"XV69G8F2B1"}],"key":"blfEVqkEcO"},{"type":"tableRow","position":{"start":{"line":17,"column":1},"end":{"line":17,"column":1}},"children":[{"type":"tableCell","align":"left","position":{"start":{"line":17,"column":1},"end":{"line":17,"column":1}},"children":[{"type":"text","value":"DN","position":{"start":{"line":17,"column":1},"end":{"line":17,"column":1}},"key":"EOWTpobUog"}],"key":"vrsJkhpyBf"},{"type":"tableCell","align":"left","position":{"start":{"line":17,"column":1},"end":{"line":17,"column":1}},"children":[{"type":"text","value":"Digital Number","position":{"start":{"line":17,"column":1},"end":{"line":17,"column":1}},"key":"RgL7rIKLTW"}],"key":"SlzOO5RCE2"}],"key":"jZQ7Z9MxhC"},{"type":"tableRow","position":{"start":{"line":18,"column":1},"end":{"line":18,"column":1}},"children":[{"type":"tableCell","align":"left","position":{"start":{"line":18,"column":1},"end":{"line":18,"column":1}},"children":[{"type":"text","value":"EAR","position":{"start":{"line":18,"column":1},"end":{"line":18,"column":1}},"key":"DcR03KjSeD"}],"key":"vXaFs2W5YB"},{"type":"tableCell","align":"left","position":{"start":{"line":18,"column":1},"end":{"line":18,"column":1}},"children":[{"type":"text","value":"Export Administration Regulations","position":{"start":{"line":18,"column":1},"end":{"line":18,"column":1}},"key":"TeRsShSTak"}],"key":"gHnMgF8Zpm"}],"key":"f1NeZGOiYS"},{"type":"tableRow","position":{"start":{"line":19,"column":1},"end":{"line":19,"column":1}},"children":[{"type":"tableCell","align":"left","position":{"start":{"line":19,"column":1},"end":{"line":19,"column":1}},"children":[{"type":"text","value":"ECMWF","position":{"start":{"line":19,"column":1},"end":{"line":19,"column":1}},"key":"p8WJE5LxS5"}],"key":"CVBSUCRZ8H"},{"type":"tableCell","align":"left","position":{"start":{"line":19,"column":1},"end":{"line":19,"column":1}},"children":[{"type":"text","value":"European Centre for Medium-Range Weather Forecasts","position":{"start":{"line":19,"column":1},"end":{"line":19,"column":1}},"key":"zqdG1iwzpR"}],"key":"PiDAPs2RYH"}],"key":"PINCt25XSw"},{"type":"tableRow","position":{"start":{"line":20,"column":1},"end":{"line":20,"column":1}},"children":[{"type":"tableCell","align":"left","position":{"start":{"line":20,"column":1},"end":{"line":20,"column":1}},"children":[{"type":"text","value":"ECEF","position":{"start":{"line":20,"column":1},"end":{"line":20,"column":1}},"key":"zMnVFDXrdy"}],"key":"y4PZbStWZ5"},{"type":"tableCell","align":"left","position":{"start":{"line":20,"column":1},"end":{"line":20,"column":1}},"children":[{"type":"text","value":"Earth Centered Earth Fixed","position":{"start":{"line":20,"column":1},"end":{"line":20,"column":1}},"key":"hIB43mOA0g"}],"key":"uXAjMgjuaE"}],"key":"oqBKo7VcOO"},{"type":"tableRow","position":{"start":{"line":21,"column":1},"end":{"line":21,"column":1}},"children":[{"type":"tableCell","align":"left","position":{"start":{"line":21,"column":1},"end":{"line":21,"column":1}},"children":[{"type":"text","value":"EPSG","position":{"start":{"line":21,"column":1},"end":{"line":21,"column":1}},"key":"v33kRiHERZ"}],"key":"XSIEw8z1eW"},{"type":"tableCell","align":"left","position":{"start":{"line":21,"column":1},"end":{"line":21,"column":1}},"children":[{"type":"text","value":"European Petroleum Survey Group","position":{"start":{"line":21,"column":1},"end":{"line":21,"column":1}},"key":"EWVpvaS2eB"}],"key":"L55E36ukVb"}],"key":"AuMElnBiBo"},{"type":"tableRow","position":{"start":{"line":22,"column":1},"end":{"line":22,"column":1}},"children":[{"type":"tableCell","align":"left","position":{"start":{"line":22,"column":1},"end":{"line":22,"column":1}},"children":[{"type":"text","value":"ESA","position":{"start":{"line":22,"column":1},"end":{"line":22,"column":1}},"key":"BtFWLhkQvY"}],"key":"Ketp3M43lx"},{"type":"tableCell","align":"left","position":{"start":{"line":22,"column":1},"end":{"line":22,"column":1}},"children":[{"type":"text","value":"European Space Agency","position":{"start":{"line":22,"column":1},"end":{"line":22,"column":1}},"key":"DpJ1ext57A"}],"key":"vrk5SNSihX"}],"key":"BKuir2y6v8"},{"type":"tableRow","position":{"start":{"line":23,"column":1},"end":{"line":23,"column":1}},"children":[{"type":"tableCell","align":"left","position":{"start":{"line":23,"column":1},"end":{"line":23,"column":1}},"children":[{"type":"text","value":"FM","position":{"start":{"line":23,"column":1},"end":{"line":23,"column":1}},"key":"KowUweXTU0"}],"key":"lmzB4kr96F"},{"type":"tableCell","align":"left","position":{"start":{"line":23,"column":1},"end":{"line":23,"column":1}},"children":[{"type":"text","value":"Frequency Modulation","position":{"start":{"line":23,"column":1},"end":{"line":23,"column":1}},"key":"Apmjci7ytH"}],"key":"V3Qo4am1oZ"}],"key":"uP8wa4SxbV"},{"type":"tableRow","position":{"start":{"line":24,"column":1},"end":{"line":24,"column":1}},"children":[{"type":"tableCell","align":"left","position":{"start":{"line":24,"column":1},"end":{"line":24,"column":1}},"children":[{"type":"text","value":"FOP","position":{"start":{"line":24,"column":1},"end":{"line":24,"column":1}},"key":"I2EOPoL676"}],"key":"o3Sk49A0kq"},{"type":"tableCell","align":"left","position":{"start":{"line":24,"column":1},"end":{"line":24,"column":1}},"children":[{"type":"text","value":"Forecast Orbit Ephemeris","position":{"start":{"line":24,"column":1},"end":{"line":24,"column":1}},"key":"BvkbZYUnn5"}],"key":"egqs1DSMUe"}],"key":"n1FlbkIyVH"},{"type":"tableRow","position":{"start":{"line":25,"column":1},"end":{"line":25,"column":1}},"children":[{"type":"tableCell","align":"left","position":{"start":{"line":25,"column":1},"end":{"line":25,"column":1}},"children":[{"type":"text","value":"FOV","position":{"start":{"line":25,"column":1},"end":{"line":25,"column":1}},"key":"TuuqHkND05"}],"key":"ptWkgEBqXJ"},{"type":"tableCell","align":"left","position":{"start":{"line":25,"column":1},"end":{"line":25,"column":1}},"children":[{"type":"text","value":"Field of View","position":{"start":{"line":25,"column":1},"end":{"line":25,"column":1}},"key":"RxaEvWdpGS"}],"key":"XojTntX3uW"}],"key":"GoaN7scA2J"},{"type":"tableRow","position":{"start":{"line":26,"column":1},"end":{"line":26,"column":1}},"children":[{"type":"tableCell","align":"left","position":{"start":{"line":26,"column":1},"end":{"line":26,"column":1}},"children":[{"type":"abbreviation","title":"Geocoded Polarimetric Covariance","children":[{"type":"text","value":"GCOV","key":"aN2Td16nBh"}],"key":"uDeWoA5haW"}],"key":"xeDBLM0Ae0"},{"type":"tableCell","align":"left","position":{"start":{"line":26,"column":1},"end":{"line":26,"column":1}},"children":[{"type":"text","value":"Geocoded Polarimetric Covariance (also as L2_","key":"ph0GFJI0dU"},{"type":"abbreviation","title":"Geocoded Polarimetric Covariance","children":[{"type":"text","value":"GCOV","key":"BHKQJHIxif"}],"key":"CjZOhEAGGY"},{"type":"text","value":")","key":"jBJrG0J8b1"}],"key":"Zg7g988qC3"}],"key":"DW3kTXyYWk"},{"type":"tableRow","position":{"start":{"line":27,"column":1},"end":{"line":27,"column":1}},"children":[{"type":"tableCell","align":"left","position":{"start":{"line":27,"column":1},"end":{"line":27,"column":1}},"children":[{"type":"text","value":"GCP","position":{"start":{"line":27,"column":1},"end":{"line":27,"column":1}},"key":"FRjEF9oT53"}],"key":"cp4DOBV80G"},{"type":"tableCell","align":"left","position":{"start":{"line":27,"column":1},"end":{"line":27,"column":1}},"children":[{"type":"text","value":"Ground Control Point","position":{"start":{"line":27,"column":1},"end":{"line":27,"column":1}},"key":"n9PLAGkc42"}],"key":"EfAdwkn7ps"}],"key":"A91OF6JoB0"},{"type":"tableRow","position":{"start":{"line":28,"column":1},"end":{"line":28,"column":1}},"children":[{"type":"tableCell","align":"left","position":{"start":{"line":28,"column":1},"end":{"line":28,"column":1}},"children":[{"type":"text","value":"GDAL","position":{"start":{"line":28,"column":1},"end":{"line":28,"column":1}},"key":"eC1Hzkzj0G"}],"key":"gZHkx0fU10"},{"type":"tableCell","align":"left","position":{"start":{"line":28,"column":1},"end":{"line":28,"column":1}},"children":[{"type":"text","value":"Geospatial Data Abstraction Library","position":{"start":{"line":28,"column":1},"end":{"line":28,"column":1}},"key":"aJOxW6EoaQ"}],"key":"KrR1JdDXT9"}],"key":"rkYiqybUYn"},{"type":"tableRow","position":{"start":{"line":29,"column":1},"end":{"line":29,"column":1}},"children":[{"type":"tableCell","align":"left","position":{"start":{"line":29,"column":1},"end":{"line":29,"column":1}},"children":[{"type":"text","value":"GDS","position":{"start":{"line":29,"column":1},"end":{"line":29,"column":1}},"key":"nS9PovmoTI"}],"key":"HiRu0sbrvH"},{"type":"tableCell","align":"left","position":{"start":{"line":29,"column":1},"end":{"line":29,"column":1}},"children":[{"type":"text","value":"Ground Data System","position":{"start":{"line":29,"column":1},"end":{"line":29,"column":1}},"key":"Np3fufa6RA"}],"key":"QNQM91qkkw"}],"key":"p7fyTeahFy"},{"type":"tableRow","position":{"start":{"line":30,"column":1},"end":{"line":30,"column":1}},"children":[{"type":"tableCell","align":"left","position":{"start":{"line":30,"column":1},"end":{"line":30,"column":1}},"children":[{"type":"text","value":"GIS","position":{"start":{"line":30,"column":1},"end":{"line":30,"column":1}},"key":"s1ydnz9pwX"}],"key":"XjSKKQcPlw"},{"type":"tableCell","align":"left","position":{"start":{"line":30,"column":1},"end":{"line":30,"column":1}},"children":[{"type":"text","value":"Geographic Information System","position":{"start":{"line":30,"column":1},"end":{"line":30,"column":1}},"key":"XKzcgzXyUv"}],"key":"oLOb7vHWzb"}],"key":"A493n1hqHW"},{"type":"tableRow","position":{"start":{"line":31,"column":1},"end":{"line":31,"column":1}},"children":[{"type":"tableCell","align":"left","position":{"start":{"line":31,"column":1},"end":{"line":31,"column":1}},"children":[{"type":"text","value":"GMTED","position":{"start":{"line":31,"column":1},"end":{"line":31,"column":1}},"key":"DkYfjZEx9H"}],"key":"YVhJWaZ7ze"},{"type":"tableCell","align":"left","position":{"start":{"line":31,"column":1},"end":{"line":31,"column":1}},"children":[{"type":"text","value":"Global Multi-resolution Terrain Elevation Data","position":{"start":{"line":31,"column":1},"end":{"line":31,"column":1}},"key":"DHKg0KDRdI"}],"key":"eOsKIzEt4c"}],"key":"dvDF0DuAPl"},{"type":"tableRow","position":{"start":{"line":32,"column":1},"end":{"line":32,"column":1}},"children":[{"type":"tableCell","align":"left","position":{"start":{"line":32,"column":1},"end":{"line":32,"column":1}},"children":[{"type":"text","value":"GNSS","position":{"start":{"line":32,"column":1},"end":{"line":32,"column":1}},"key":"VZyhkHcAML"}],"key":"JnGpMnHsu7"},{"type":"tableCell","align":"left","position":{"start":{"line":32,"column":1},"end":{"line":32,"column":1}},"children":[{"type":"text","value":"Global Navigation Satellite System","position":{"start":{"line":32,"column":1},"end":{"line":32,"column":1}},"key":"LvxfCimZhT"}],"key":"GUoui4fBY6"}],"key":"ryStIgrwet"},{"type":"tableRow","position":{"start":{"line":33,"column":1},"end":{"line":33,"column":1}},"children":[{"type":"tableCell","align":"left","position":{"start":{"line":33,"column":1},"end":{"line":33,"column":1}},"children":[{"type":"abbreviation","title":"Geocoded Pixel Offsets","children":[{"type":"text","value":"GOFF","key":"dJtRgYwYnh"}],"key":"Bg5q4wDkjL"}],"key":"LgDm3EQIdT"},{"type":"tableCell","align":"left","position":{"start":{"line":33,"column":1},"end":{"line":33,"column":1}},"children":[{"type":"text","value":"Geocoded Pixel Offsets (also as L2_","key":"DkQ0mGSb5Q"},{"type":"abbreviation","title":"Geocoded Pixel Offsets","children":[{"type":"text","value":"GOFF","key":"Sn3TQZnvSu"}],"key":"SuHBBVeKls"},{"type":"text","value":")","key":"PwnrQrAypw"}],"key":"xdYyoGhHQP"}],"key":"xxbNPOByMm"},{"type":"tableRow","position":{"start":{"line":34,"column":1},"end":{"line":34,"column":1}},"children":[{"type":"tableCell","align":"left","position":{"start":{"line":34,"column":1},"end":{"line":34,"column":1}},"children":[{"type":"text","value":"GPU","position":{"start":{"line":34,"column":1},"end":{"line":34,"column":1}},"key":"EfxI1LxNgW"}],"key":"pn2GBT93c6"},{"type":"tableCell","align":"left","position":{"start":{"line":34,"column":1},"end":{"line":34,"column":1}},"children":[{"type":"text","value":"Graphics Processing Unit","position":{"start":{"line":34,"column":1},"end":{"line":34,"column":1}},"key":"v4ALAYGbLE"}],"key":"LF4r0nrPqS"}],"key":"Hi4v9uXnVr"},{"type":"tableRow","position":{"start":{"line":35,"column":1},"end":{"line":35,"column":1}},"children":[{"type":"tableCell","align":"left","position":{"start":{"line":35,"column":1},"end":{"line":35,"column":1}},"children":[{"type":"abbreviation","title":"Geocoded Single Look Complex","children":[{"type":"text","value":"GSLC","key":"OBfmNJ9QcO"}],"key":"kWJDS8KESd"}],"key":"kSXVwm2OoJ"},{"type":"tableCell","align":"left","position":{"start":{"line":35,"column":1},"end":{"line":35,"column":1}},"children":[{"type":"text","value":"Geocoded Single Look Complex (also as L2_","key":"eZgg0RcdhC"},{"type":"abbreviation","title":"Geocoded Single Look Complex","children":[{"type":"text","value":"GSLC","key":"ROvTP9ALKX"}],"key":"W368jzMPyW"},{"type":"text","value":")","key":"Fq4OOCpUOg"}],"key":"ABvhgU5pqE"}],"key":"dEXCCPti63"},{"type":"tableRow","position":{"start":{"line":36,"column":1},"end":{"line":36,"column":1}},"children":[{"type":"tableCell","align":"left","position":{"start":{"line":36,"column":1},"end":{"line":36,"column":1}},"children":[{"type":"abbreviation","title":"Geocoded Unwrapped Interferogram","children":[{"type":"text","value":"GUNW","key":"VlLCfGtIq2"}],"key":"GqX2bdoYnf"}],"key":"N4yFCLh0v8"},{"type":"tableCell","align":"left","position":{"start":{"line":36,"column":1},"end":{"line":36,"column":1}},"children":[{"type":"text","value":"Geocoded d Unwrapped Interferogram (also as L2_","key":"wxmNlFeOVE"},{"type":"abbreviation","title":"Geocoded Unwrapped Interferogram","children":[{"type":"text","value":"GUNW","key":"hMcTx47Ikt"}],"key":"cucRIOlvyi"},{"type":"text","value":")","key":"OQl4DmkduC"}],"key":"HeQjoRRpIg"}],"key":"d9eSrjFhwJ"},{"type":"tableRow","position":{"start":{"line":37,"column":1},"end":{"line":37,"column":1}},"children":[{"type":"tableCell","align":"left","position":{"start":{"line":37,"column":1},"end":{"line":37,"column":1}},"children":[{"type":"text","value":"HDF5","position":{"start":{"line":37,"column":1},"end":{"line":37,"column":1}},"key":"MOgbUMNfz5"}],"key":"Y3w7TGuMrp"},{"type":"tableCell","align":"left","position":{"start":{"line":37,"column":1},"end":{"line":37,"column":1}},"children":[{"type":"text","value":"Hierarchical Data Format version 5","position":{"start":{"line":37,"column":1},"end":{"line":37,"column":1}},"key":"OhaEthPu9A"}],"key":"IObe6cu6l5"}],"key":"x3FAqtN7b0"},{"type":"tableRow","position":{"start":{"line":38,"column":1},"end":{"line":38,"column":1}},"children":[{"type":"tableCell","align":"left","position":{"start":{"line":38,"column":1},"end":{"line":38,"column":1}},"children":[{"type":"text","value":"HK,HKTM","position":{"start":{"line":38,"column":1},"end":{"line":38,"column":1}},"key":"UVc4skqpG1"}],"key":"S9Cr5Zi6WA"},{"type":"tableCell","align":"left","position":{"start":{"line":38,"column":1},"end":{"line":38,"column":1}},"children":[{"type":"text","value":"Housekeeping Telemetry","position":{"start":{"line":38,"column":1},"end":{"line":38,"column":1}},"key":"ASlgrWlDBI"}],"key":"xSZqxUV4SO"}],"key":"zwCHxsFG44"},{"type":"tableRow","position":{"start":{"line":39,"column":1},"end":{"line":39,"column":1}},"children":[{"type":"tableCell","align":"left","position":{"start":{"line":39,"column":1},"end":{"line":39,"column":1}},"children":[{"type":"text","value":"In","key":"U2dQ3bf8QM"},{"type":"abbreviation","title":"Synthetic Aperture Radar","children":[{"type":"text","value":"SAR","key":"d1h3D1APOJ"}],"key":"x1Njahycov"}],"key":"H6NeLR9KDw"},{"type":"tableCell","align":"left","position":{"start":{"line":39,"column":1},"end":{"line":39,"column":1}},"children":[{"type":"text","value":"Interferometric Synthetic Aperture Radar","position":{"start":{"line":39,"column":1},"end":{"line":39,"column":1}},"key":"dH36K33fOC"}],"key":"QyiHwZXoqA"}],"key":"YxANo7856S"},{"type":"tableRow","position":{"start":{"line":40,"column":1},"end":{"line":40,"column":1}},"children":[{"type":"tableCell","align":"left","position":{"start":{"line":40,"column":1},"end":{"line":40,"column":1}},"children":[{"type":"text","value":"ISCE","position":{"start":{"line":40,"column":1},"end":{"line":40,"column":1}},"key":"LRSbzs148d"}],"key":"pUlnsm1aXy"},{"type":"tableCell","align":"left","position":{"start":{"line":40,"column":1},"end":{"line":40,"column":1}},"children":[{"type":"text","value":"In","key":"IT8qXf0Qju"},{"type":"abbreviation","title":"Synthetic Aperture Radar","children":[{"type":"text","value":"SAR","key":"BJpC9WOu8j"}],"key":"kqUhf34ex0"},{"type":"text","value":" Scientific Computing Environment","key":"gxy3z1w7VD"}],"key":"ST4phN7rY7"}],"key":"VM0NJi2rh6"},{"type":"tableRow","position":{"start":{"line":41,"column":1},"end":{"line":41,"column":1}},"children":[{"type":"tableCell","align":"left","position":{"start":{"line":41,"column":1},"end":{"line":41,"column":1}},"children":[{"type":"text","value":"ISCE3","position":{"start":{"line":41,"column":1},"end":{"line":41,"column":1}},"key":"GN1bwasVIN"}],"key":"JYT4zfi2MD"},{"type":"tableCell","align":"left","position":{"start":{"line":41,"column":1},"end":{"line":41,"column":1}},"children":[{"type":"text","value":"In","key":"v6uyqBRzB0"},{"type":"abbreviation","title":"Synthetic Aperture Radar","children":[{"type":"text","value":"SAR","key":"nBm4lMH68v"}],"key":"y7TVu23KJ4"},{"type":"text","value":" Scientific Computing Environment Enhanced Edition (for ","key":"QcQEoLiFEa"},{"type":"abbreviation","title":"NASA-ISRO Synthetic Aperture Radar","children":[{"type":"text","value":"NISAR","key":"JKprcQMdI5"}],"key":"NCFXulJ4sE"},{"type":"text","value":")","key":"poRaKV9CCD"}],"key":"jwtcP2B4cw"}],"key":"iekGMtn75U"},{"type":"tableRow","position":{"start":{"line":42,"column":1},"end":{"line":42,"column":1}},"children":[{"type":"tableCell","align":"left","position":{"start":{"line":42,"column":1},"end":{"line":42,"column":1}},"children":[{"type":"text","value":"ISO","position":{"start":{"line":42,"column":1},"end":{"line":42,"column":1}},"key":"MrTLkXEYX2"}],"key":"RE9Y4AC71W"},{"type":"tableCell","align":"left","position":{"start":{"line":42,"column":1},"end":{"line":42,"column":1}},"children":[{"type":"text","value":"International Organization for Standardization","position":{"start":{"line":42,"column":1},"end":{"line":42,"column":1}},"key":"bCqcPEKR5W"}],"key":"jS2T5s7er0"}],"key":"BHOKsnI9KX"},{"type":"tableRow","position":{"start":{"line":43,"column":1},"end":{"line":43,"column":1}},"children":[{"type":"tableCell","align":"left","position":{"start":{"line":43,"column":1},"end":{"line":43,"column":1}},"children":[{"type":"text","value":"ISRO","position":{"start":{"line":43,"column":1},"end":{"line":43,"column":1}},"key":"fNiKSRPilO"}],"key":"cGMXVnE8uC"},{"type":"tableCell","align":"left","position":{"start":{"line":43,"column":1},"end":{"line":43,"column":1}},"children":[{"type":"text","value":"Indian Space Research Organisation (British spelling)","position":{"start":{"line":43,"column":1},"end":{"line":43,"column":1}},"key":"bSPd3shIRJ"}],"key":"lAhTwtpNOz"}],"key":"MEF3SrymgE"},{"type":"tableRow","position":{"start":{"line":44,"column":1},"end":{"line":44,"column":1}},"children":[{"type":"tableCell","align":"left","position":{"start":{"line":44,"column":1},"end":{"line":44,"column":1}},"children":[{"type":"text","value":"L0B","position":{"start":{"line":44,"column":1},"end":{"line":44,"column":1}},"key":"zCOwd0rI8l"}],"key":"jS9xshplvM"},{"type":"tableCell","align":"left","position":{"start":{"line":44,"column":1},"end":{"line":44,"column":1}},"children":[{"type":"text","value":"Level-0B (data)","position":{"start":{"line":44,"column":1},"end":{"line":44,"column":1}},"key":"ug8n6EUz53"}],"key":"bUzMmtmpOD"}],"key":"To3PnqHq8F"},{"type":"tableRow","position":{"start":{"line":45,"column":1},"end":{"line":45,"column":1}},"children":[{"type":"tableCell","align":"left","position":{"start":{"line":45,"column":1},"end":{"line":45,"column":1}},"children":[{"type":"text","value":"L1","position":{"start":{"line":45,"column":1},"end":{"line":45,"column":1}},"key":"DFUzOy8vpK"}],"key":"ijWckbpuF0"},{"type":"tableCell","align":"left","position":{"start":{"line":45,"column":1},"end":{"line":45,"column":1}},"children":[{"type":"text","value":"Level-1 (data)","position":{"start":{"line":45,"column":1},"end":{"line":45,"column":1}},"key":"XXEvDf6v0f"}],"key":"cfaKkREYmN"}],"key":"s2gFgRg83A"},{"type":"tableRow","position":{"start":{"line":46,"column":1},"end":{"line":46,"column":1}},"children":[{"type":"tableCell","align":"left","position":{"start":{"line":46,"column":1},"end":{"line":46,"column":1}},"children":[{"type":"text","value":"L2","position":{"start":{"line":46,"column":1},"end":{"line":46,"column":1}},"key":"uTppZ3DxIR"}],"key":"FpXvat3Pfz"},{"type":"tableCell","align":"left","position":{"start":{"line":46,"column":1},"end":{"line":46,"column":1}},"children":[{"type":"text","value":"Level-2 (data)","position":{"start":{"line":46,"column":1},"end":{"line":46,"column":1}},"key":"NofnMNoUhh"}],"key":"SagE1Zehb5"}],"key":"o8V8txGzlQ"},{"type":"tableRow","position":{"start":{"line":47,"column":1},"end":{"line":47,"column":1}},"children":[{"type":"tableCell","align":"left","position":{"start":{"line":47,"column":1},"end":{"line":47,"column":1}},"children":[{"type":"text","value":"LOS","position":{"start":{"line":47,"column":1},"end":{"line":47,"column":1}},"key":"N8TAoPRC0U"}],"key":"WNHgvjfnwB"},{"type":"tableCell","align":"left","position":{"start":{"line":47,"column":1},"end":{"line":47,"column":1}},"children":[{"type":"text","value":"Line-Of-Sight","position":{"start":{"line":47,"column":1},"end":{"line":47,"column":1}},"key":"jxfJ4ox2J6"}],"key":"hxMNN5kxF7"}],"key":"JjPK4gYPBh"},{"type":"tableRow","position":{"start":{"line":48,"column":1},"end":{"line":48,"column":1}},"children":[{"type":"tableCell","align":"left","position":{"start":{"line":48,"column":1},"end":{"line":48,"column":1}},"children":[{"type":"text","value":"LUT","position":{"start":{"line":48,"column":1},"end":{"line":48,"column":1}},"key":"tBcNoHtk7a"}],"key":"JAJK7kwQtB"},{"type":"tableCell","align":"left","position":{"start":{"line":48,"column":1},"end":{"line":48,"column":1}},"children":[{"type":"text","value":"Lookup Table","position":{"start":{"line":48,"column":1},"end":{"line":48,"column":1}},"key":"cQuLoKiYo2"}],"key":"eXOKFKaqLO"}],"key":"RoPZd7CHyV"},{"type":"tableRow","position":{"start":{"line":49,"column":1},"end":{"line":49,"column":1}},"children":[{"type":"tableCell","align":"left","position":{"start":{"line":49,"column":1},"end":{"line":49,"column":1}},"children":[{"type":"text","value":"Mbps","position":{"start":{"line":49,"column":1},"end":{"line":49,"column":1}},"key":"mV01kmdzrq"}],"key":"mNEjiFQIWU"},{"type":"tableCell","align":"left","position":{"start":{"line":49,"column":1},"end":{"line":49,"column":1}},"children":[{"type":"text","value":"Megabits per second","position":{"start":{"line":49,"column":1},"end":{"line":49,"column":1}},"key":"vQHmNftYcj"}],"key":"QCqYzTEC1M"}],"key":"v61Avko37y"},{"type":"tableRow","position":{"start":{"line":50,"column":1},"end":{"line":50,"column":1}},"children":[{"type":"tableCell","align":"left","position":{"start":{"line":50,"column":1},"end":{"line":50,"column":1}},"children":[{"type":"text","value":"MHz","position":{"start":{"line":50,"column":1},"end":{"line":50,"column":1}},"key":"lTquX5rqFg"}],"key":"TcWdfsKWdI"},{"type":"tableCell","align":"left","position":{"start":{"line":50,"column":1},"end":{"line":50,"column":1}},"children":[{"type":"text","value":"Megahertz","position":{"start":{"line":50,"column":1},"end":{"line":50,"column":1}},"key":"s6a7r7U6p3"}],"key":"WBOc1Ra4oB"}],"key":"IDHay6fRTv"},{"type":"tableRow","position":{"start":{"line":51,"column":1},"end":{"line":51,"column":1}},"children":[{"type":"tableCell","align":"left","position":{"start":{"line":51,"column":1},"end":{"line":51,"column":1}},"children":[{"type":"text","value":"MOE","position":{"start":{"line":51,"column":1},"end":{"line":51,"column":1}},"key":"ZEmc3gcCqx"}],"key":"dOozkJSk9L"},{"type":"tableCell","align":"left","position":{"start":{"line":51,"column":1},"end":{"line":51,"column":1}},"children":[{"type":"text","value":"Medium-precision Orbit Ephemeris","position":{"start":{"line":51,"column":1},"end":{"line":51,"column":1}},"key":"yj1QNVrTgg"}],"key":"HBWcjLcB8K"}],"key":"Iy7jEBJyef"},{"type":"tableRow","position":{"start":{"line":52,"column":1},"end":{"line":52,"column":1}},"children":[{"type":"tableCell","align":"left","position":{"start":{"line":52,"column":1},"end":{"line":52,"column":1}},"children":[{"type":"text","value":"NCSA","position":{"start":{"line":52,"column":1},"end":{"line":52,"column":1}},"key":"f4h3w1BQgj"}],"key":"OYGF3IvsTl"},{"type":"tableCell","align":"left","position":{"start":{"line":52,"column":1},"end":{"line":52,"column":1}},"children":[{"type":"text","value":"National Center for Supercomputing Applications","position":{"start":{"line":52,"column":1},"end":{"line":52,"column":1}},"key":"rdc1dCnknx"}],"key":"qhYit3fGvW"}],"key":"WZr9eORFbC"},{"type":"tableRow","position":{"start":{"line":53,"column":1},"end":{"line":53,"column":1}},"children":[{"type":"tableCell","align":"left","position":{"start":{"line":53,"column":1},"end":{"line":53,"column":1}},"children":[{"type":"text","value":"NetCDF4","position":{"start":{"line":53,"column":1},"end":{"line":53,"column":1}},"key":"wXVDrDW8Y1"}],"key":"rTpL3EjUU9"},{"type":"tableCell","align":"left","position":{"start":{"line":53,"column":1},"end":{"line":53,"column":1}},"children":[{"type":"text","value":"Network Common Data Form version 4","position":{"start":{"line":53,"column":1},"end":{"line":53,"column":1}},"key":"ahFi8RQJsx"}],"key":"RynQIuane6"}],"key":"dPMMyG7AKg"},{"type":"tableRow","position":{"start":{"line":54,"column":1},"end":{"line":54,"column":1}},"children":[{"type":"tableCell","align":"left","position":{"start":{"line":54,"column":1},"end":{"line":54,"column":1}},"children":[{"type":"abbreviation","title":"NASA-ISRO Synthetic Aperture Radar","children":[{"type":"text","value":"NISAR","key":"cMj3wHBTkF"}],"key":"rhrzCGqMFD"}],"key":"a2HSEAErRw"},{"type":"tableCell","align":"left","position":{"start":{"line":54,"column":1},"end":{"line":54,"column":1}},"children":[{"type":"text","value":"NASA-ISRO Synthetic Aperture Radar","position":{"start":{"line":54,"column":1},"end":{"line":54,"column":1}},"key":"ERRgEwYLV2"}],"key":"Wxc8RPFTvh"}],"key":"Zr54vjDE98"},{"type":"tableRow","position":{"start":{"line":55,"column":1},"end":{"line":55,"column":1}},"children":[{"type":"tableCell","align":"left","position":{"start":{"line":55,"column":1},"end":{"line":55,"column":1}},"children":[{"type":"text","value":"NOE","position":{"start":{"line":55,"column":1},"end":{"line":55,"column":1}},"key":"RvLurvp1Wd"}],"key":"NE5wGwhDh3"},{"type":"tableCell","align":"left","position":{"start":{"line":55,"column":1},"end":{"line":55,"column":1}},"children":[{"type":"text","value":"Near-Realtime Orbit Ephemeris","position":{"start":{"line":55,"column":1},"end":{"line":55,"column":1}},"key":"hui7rXSk1n"}],"key":"AhQdK0puun"}],"key":"lv2BVPyKKk"},{"type":"tableRow","position":{"start":{"line":56,"column":1},"end":{"line":56,"column":1}},"children":[{"type":"tableCell","align":"left","position":{"start":{"line":56,"column":1},"end":{"line":56,"column":1}},"children":[{"type":"text","value":"PDR","position":{"start":{"line":56,"column":1},"end":{"line":56,"column":1}},"key":"D5BPk6yOwk"}],"key":"ECHfX1Aafz"},{"type":"tableCell","align":"left","position":{"start":{"line":56,"column":1},"end":{"line":56,"column":1}},"children":[{"type":"text","value":"Preliminary Design Review","position":{"start":{"line":56,"column":1},"end":{"line":56,"column":1}},"key":"U1DdyltFfg"}],"key":"UKSdrqUby8"}],"key":"XBCZ4ZNXx4"},{"type":"tableRow","position":{"start":{"line":57,"column":1},"end":{"line":57,"column":1}},"children":[{"type":"tableCell","align":"left","position":{"start":{"line":57,"column":1},"end":{"line":57,"column":1}},"children":[{"type":"text","value":"PLM","position":{"start":{"line":57,"column":1},"end":{"line":57,"column":1}},"key":"solqNPWkyq"}],"key":"h0lkGpuHNs"},{"type":"tableCell","align":"left","position":{"start":{"line":57,"column":1},"end":{"line":57,"column":1}},"children":[{"type":"text","value":"Product Lifecycle Management","position":{"start":{"line":57,"column":1},"end":{"line":57,"column":1}},"key":"sqFjd0obAt"}],"key":"sQigPCYbEK"}],"key":"AlfkKaSiLQ"},{"type":"tableRow","position":{"start":{"line":58,"column":1},"end":{"line":58,"column":1}},"children":[{"type":"tableCell","align":"left","position":{"start":{"line":58,"column":1},"end":{"line":58,"column":1}},"children":[{"type":"text","value":"POD","position":{"start":{"line":58,"column":1},"end":{"line":58,"column":1}},"key":"dbYA0Ksqga"}],"key":"LmrYde5ERr"},{"type":"tableCell","align":"left","position":{"start":{"line":58,"column":1},"end":{"line":58,"column":1}},"children":[{"type":"text","value":"Precision Orbit Determination","position":{"start":{"line":58,"column":1},"end":{"line":58,"column":1}},"key":"AOtEbOyl60"}],"key":"Uwmv5XLIkA"}],"key":"AmG5sZGX1f"},{"type":"tableRow","position":{"start":{"line":59,"column":1},"end":{"line":59,"column":1}},"children":[{"type":"tableCell","align":"left","position":{"start":{"line":59,"column":1},"end":{"line":59,"column":1}},"children":[{"type":"text","value":"POE","position":{"start":{"line":59,"column":1},"end":{"line":59,"column":1}},"key":"SpHk8ioRv5"}],"key":"Dkoek4GFUW"},{"type":"tableCell","align":"left","position":{"start":{"line":59,"column":1},"end":{"line":59,"column":1}},"children":[{"type":"text","value":"Precision Orbit Ephemeris","position":{"start":{"line":59,"column":1},"end":{"line":59,"column":1}},"key":"Vqz7bRhjXo"}],"key":"pw7k2qP0QL"}],"key":"NG3yuzpbUo"},{"type":"tableRow","position":{"start":{"line":60,"column":1},"end":{"line":60,"column":1}},"children":[{"type":"tableCell","align":"left","position":{"start":{"line":60,"column":1},"end":{"line":60,"column":1}},"children":[{"type":"text","value":"PRF","position":{"start":{"line":60,"column":1},"end":{"line":60,"column":1}},"key":"zuaXYbuPgp"}],"key":"qm8yPXqNfM"},{"type":"tableCell","align":"left","position":{"start":{"line":60,"column":1},"end":{"line":60,"column":1}},"children":[{"type":"text","value":"Pulse Repetition Frequency","position":{"start":{"line":60,"column":1},"end":{"line":60,"column":1}},"key":"f6UvzjcY51"}],"key":"zN6xA0Utn6"}],"key":"TJBunM6nPl"},{"type":"tableRow","position":{"start":{"line":61,"column":1},"end":{"line":61,"column":1}},"children":[{"type":"tableCell","align":"left","position":{"start":{"line":61,"column":1},"end":{"line":61,"column":1}},"children":[{"type":"text","value":"QA","position":{"start":{"line":61,"column":1},"end":{"line":61,"column":1}},"key":"YzismUXZxR"}],"key":"yQtisnFeao"},{"type":"tableCell","align":"left","position":{"start":{"line":61,"column":1},"end":{"line":61,"column":1}},"children":[{"type":"text","value":"Quality Assurance","position":{"start":{"line":61,"column":1},"end":{"line":61,"column":1}},"key":"oDvyyT5hfv"}],"key":"a8zfUAof28"}],"key":"DKs6v55fcQ"},{"type":"tableRow","position":{"start":{"line":62,"column":1},"end":{"line":62,"column":1}},"children":[{"type":"tableCell","align":"left","position":{"start":{"line":62,"column":1},"end":{"line":62,"column":1}},"children":[{"type":"text","value":"REE","position":{"start":{"line":62,"column":1},"end":{"line":62,"column":1}},"key":"hePO1gPBxc"}],"key":"WImz7CAe25"},{"type":"tableCell","align":"left","position":{"start":{"line":62,"column":1},"end":{"line":62,"column":1}},"children":[{"type":"text","value":"Radar Echo Emulator","position":{"start":{"line":62,"column":1},"end":{"line":62,"column":1}},"key":"qLsvm1S8dF"}],"key":"TFKSf3wwfb"}],"key":"bjk5d0V8Qc"},{"type":"tableRow","position":{"start":{"line":63,"column":1},"end":{"line":63,"column":1}},"children":[{"type":"tableCell","align":"left","position":{"start":{"line":63,"column":1},"end":{"line":63,"column":1}},"children":[{"type":"text","value":"RFI","position":{"start":{"line":63,"column":1},"end":{"line":63,"column":1}},"key":"coVpSJ3UpV"}],"key":"e6b7i9WnYK"},{"type":"tableCell","align":"left","position":{"start":{"line":63,"column":1},"end":{"line":63,"column":1}},"children":[{"type":"text","value":"Radio Frequency Interference","position":{"start":{"line":63,"column":1},"end":{"line":63,"column":1}},"key":"FCJA7JKBHv"}],"key":"wsPeLClDQ3"}],"key":"GvCTjyfY7v"},{"type":"tableRow","position":{"start":{"line":64,"column":1},"end":{"line":64,"column":1}},"children":[{"type":"tableCell","align":"left","position":{"start":{"line":64,"column":1},"end":{"line":64,"column":1}},"children":[{"type":"abbreviation","title":"Range Doppler Wrapped Interferogram","children":[{"type":"text","value":"RIFG","key":"K08iMXMt9v"}],"key":"MKWadtpLFF"}],"key":"EAAjRWKvGP"},{"type":"tableCell","align":"left","position":{"start":{"line":64,"column":1},"end":{"line":64,"column":1}},"children":[{"type":"text","value":"Range-Doppler Interferogram (also as L1_","key":"PNvU51E6Iw"},{"type":"abbreviation","title":"Range Doppler Wrapped Interferogram","children":[{"type":"text","value":"RIFG","key":"tB7n6V9dfS"}],"key":"fgiKqYl70Y"},{"type":"text","value":")","key":"z56S5Klzdq"}],"key":"V8eEcYQRfQ"}],"key":"zvhNteTzIp"},{"type":"tableRow","position":{"start":{"line":65,"column":1},"end":{"line":65,"column":1}},"children":[{"type":"tableCell","align":"left","position":{"start":{"line":65,"column":1},"end":{"line":65,"column":1}},"children":[{"type":"abbreviation","title":"Range Doppler Pixel Offsets","children":[{"type":"text","value":"ROFF","key":"ODxGXzFILx"}],"key":"s25oFtFNk2"}],"key":"vwJidpiB40"},{"type":"tableCell","align":"left","position":{"start":{"line":65,"column":1},"end":{"line":65,"column":1}},"children":[{"type":"text","value":"Range-Doppler Pixel Offsets (also as L1_","key":"uVXY0krVj9"},{"type":"abbreviation","title":"Range Doppler Pixel Offsets","children":[{"type":"text","value":"ROFF","key":"uX1bVfl8tD"}],"key":"ajnqJTrbKG"},{"type":"text","value":")","key":"QGaVBXwbK5"}],"key":"UKQsPR4WuB"}],"key":"F52i6EUr9e"},{"type":"tableRow","position":{"start":{"line":66,"column":1},"end":{"line":66,"column":1}},"children":[{"type":"tableCell","align":"left","position":{"start":{"line":66,"column":1},"end":{"line":66,"column":1}},"children":[{"type":"abbreviation","title":"Radar Raw Signal Data","children":[{"type":"text","value":"RRSD","key":"Guq9qSj48m"}],"key":"XAGYRLw3EX"}],"key":"mw3j6hh1u9"},{"type":"tableCell","align":"left","position":{"start":{"line":66,"column":1},"end":{"line":66,"column":1}},"children":[{"type":"text","value":"Radar Raw Signal Data","position":{"start":{"line":66,"column":1},"end":{"line":66,"column":1}},"key":"R5bqnyRgLW"}],"key":"T4IPw7vB9K"}],"key":"m4wPxWsNZ1"},{"type":"tableRow","position":{"start":{"line":67,"column":1},"end":{"line":67,"column":1}},"children":[{"type":"tableCell","align":"left","position":{"start":{"line":67,"column":1},"end":{"line":67,"column":1}},"children":[{"type":"text","value":"RRST","position":{"start":{"line":67,"column":1},"end":{"line":67,"column":1}},"key":"tQg1kEcnZj"}],"key":"PsGGuZIjjb"},{"type":"tableCell","align":"left","position":{"start":{"line":67,"column":1},"end":{"line":67,"column":1}},"children":[{"type":"text","value":"Radar Raw Science Telemetry","position":{"start":{"line":67,"column":1},"end":{"line":67,"column":1}},"key":"TaYQ3mNb9R"}],"key":"fjzMgXQJTJ"}],"key":"Cy00PsBmEU"},{"type":"tableRow","position":{"start":{"line":68,"column":1},"end":{"line":68,"column":1}},"children":[{"type":"tableCell","align":"left","position":{"start":{"line":68,"column":1},"end":{"line":68,"column":1}},"children":[{"type":"abbreviation","title":"Range Doppler Single Look Complex","children":[{"type":"text","value":"RSLC","key":"elBBFLIAzS"}],"key":"GMTJtQeLx2"}],"key":"U2Qa6SwLBw"},{"type":"tableCell","align":"left","position":{"start":{"line":68,"column":1},"end":{"line":68,"column":1}},"children":[{"type":"text","value":"Range-Doppler Single Look Complex (also as L1_","key":"tRRj9Sm3zB"},{"type":"abbreviation","title":"Range Doppler Single Look Complex","children":[{"type":"text","value":"RSLC","key":"Vxkazz6F0r"}],"key":"S0TDwuCnFw"},{"type":"text","value":")","key":"LLKPgFn9tz"}],"key":"CrJxOyTw9S"}],"key":"GbflkrxLIp"},{"type":"tableRow","position":{"start":{"line":69,"column":1},"end":{"line":69,"column":1}},"children":[{"type":"tableCell","align":"left","position":{"start":{"line":69,"column":1},"end":{"line":69,"column":1}},"children":[{"type":"abbreviation","title":"Range Doppler Unwrapped Interferogram","children":[{"type":"text","value":"RUNW","key":"EPzWECOHHS"}],"key":"SZS3PpGj2U"}],"key":"Ugk3sBMdnK"},{"type":"tableCell","align":"left","position":{"start":{"line":69,"column":1},"end":{"line":69,"column":1}},"children":[{"type":"text","value":"Range-Doppler UnWrapped Interferogram (also as L1_","key":"c7nD0ui1Xa"},{"type":"abbreviation","title":"Range Doppler Unwrapped Interferogram","children":[{"type":"text","value":"RUNW","key":"r3ba0WRSkb"}],"key":"ruKIXrHZGt"},{"type":"text","value":")","key":"rn6tA3blsX"}],"key":"jpJ4L0tUTD"}],"key":"JYLNFarJ9c"},{"type":"tableRow","position":{"start":{"line":70,"column":1},"end":{"line":70,"column":1}},"children":[{"type":"tableCell","align":"left","position":{"start":{"line":70,"column":1},"end":{"line":70,"column":1}},"children":[{"type":"abbreviation","title":"Synthetic Aperture Radar","children":[{"type":"text","value":"SAR","key":"pAMVHbOZju"}],"key":"BXAdUz89gZ"}],"key":"er1DnnCXrZ"},{"type":"tableCell","align":"left","position":{"start":{"line":70,"column":1},"end":{"line":70,"column":1}},"children":[{"type":"text","value":"Synthetic Aperture Radar","position":{"start":{"line":70,"column":1},"end":{"line":70,"column":1}},"key":"DyDQTWpQyv"}],"key":"a13bDElrUr"}],"key":"xLFb85EIlR"},{"type":"tableRow","position":{"start":{"line":71,"column":1},"end":{"line":71,"column":1}},"children":[{"type":"tableCell","align":"left","position":{"start":{"line":71,"column":1},"end":{"line":71,"column":1}},"children":[{"type":"text","value":"SAS","position":{"start":{"line":71,"column":1},"end":{"line":71,"column":1}},"key":"W93ERNp0f6"}],"key":"wo77hMCnak"},{"type":"tableCell","align":"left","position":{"start":{"line":71,"column":1},"end":{"line":71,"column":1}},"children":[{"type":"text","value":"Science Algorithm Software","position":{"start":{"line":71,"column":1},"end":{"line":71,"column":1}},"key":"g5mWTKZQoI"}],"key":"rRFFu1zzmi"}],"key":"naVsMo82t2"},{"type":"tableRow","position":{"start":{"line":72,"column":1},"end":{"line":72,"column":1}},"children":[{"type":"tableCell","align":"left","position":{"start":{"line":72,"column":1},"end":{"line":72,"column":1}},"children":[{"type":"text","value":"SDS","position":{"start":{"line":72,"column":1},"end":{"line":72,"column":1}},"key":"rsM6Sb4H7H"}],"key":"lnRY8GWFKI"},{"type":"tableCell","align":"left","position":{"start":{"line":72,"column":1},"end":{"line":72,"column":1}},"children":[{"type":"text","value":"Science Data System","position":{"start":{"line":72,"column":1},"end":{"line":72,"column":1}},"key":"Tyc3DzggWj"}],"key":"G3xUHiUvJs"}],"key":"R5fHTM0Jpr"},{"type":"tableRow","position":{"start":{"line":73,"column":1},"end":{"line":73,"column":1}},"children":[{"type":"tableCell","align":"left","position":{"start":{"line":73,"column":1},"end":{"line":73,"column":1}},"children":[{"type":"text","value":"SDT","position":{"start":{"line":73,"column":1},"end":{"line":73,"column":1}},"key":"SyeAszcWJR"}],"key":"D5ZF9ZFC1K"},{"type":"tableCell","align":"left","position":{"start":{"line":73,"column":1},"end":{"line":73,"column":1}},"children":[{"type":"text","value":"Science Definition Team","position":{"start":{"line":73,"column":1},"end":{"line":73,"column":1}},"key":"IIkfvsuD5g"}],"key":"xUXsDON6pe"}],"key":"Om5b9Htb9k"},{"type":"tableRow","position":{"start":{"line":74,"column":1},"end":{"line":74,"column":1}},"children":[{"type":"tableCell","align":"left","position":{"start":{"line":74,"column":1},"end":{"line":74,"column":1}},"children":[{"type":"text","value":"SIS","position":{"start":{"line":74,"column":1},"end":{"line":74,"column":1}},"key":"OU2BOfyQVD"}],"key":"BRXhLLcKJg"},{"type":"tableCell","align":"left","position":{"start":{"line":74,"column":1},"end":{"line":74,"column":1}},"children":[{"type":"text","value":"Software Interface Specification","position":{"start":{"line":74,"column":1},"end":{"line":74,"column":1}},"key":"Ipta206XKu"}],"key":"HQWhOFxlMu"}],"key":"IkuC1keTiG"},{"type":"tableRow","position":{"start":{"line":75,"column":1},"end":{"line":75,"column":1}},"children":[{"type":"tableCell","align":"left","position":{"start":{"line":75,"column":1},"end":{"line":75,"column":1}},"children":[{"type":"text","value":"SLC","position":{"start":{"line":75,"column":1},"end":{"line":75,"column":1}},"key":"VxHxObMSmE"}],"key":"zCYYBANNKP"},{"type":"tableCell","align":"left","position":{"start":{"line":75,"column":1},"end":{"line":75,"column":1}},"children":[{"type":"text","value":"Single Look Complex","position":{"start":{"line":75,"column":1},"end":{"line":75,"column":1}},"key":"aSG537t1Wv"}],"key":"QedwYnToJj"}],"key":"vXwcemcC6Q"},{"type":"tableRow","position":{"start":{"line":76,"column":1},"end":{"line":76,"column":1}},"children":[{"type":"tableCell","align":"left","position":{"start":{"line":76,"column":1},"end":{"line":76,"column":1}},"children":[{"type":"text","value":"SNAPHU","position":{"start":{"line":76,"column":1},"end":{"line":76,"column":1}},"key":"C4fav3UVgV"}],"key":"sYe942zKGW"},{"type":"tableCell","align":"left","position":{"start":{"line":76,"column":1},"end":{"line":76,"column":1}},"children":[{"type":"text","value":"Statistical-cost, Network-flow Algorithm for Phase Unwrapping","position":{"start":{"line":76,"column":1},"end":{"line":76,"column":1}},"key":"CBywpM09SS"}],"key":"Hp3CDv56ve"}],"key":"rkssCGsoMB"},{"type":"tableRow","position":{"start":{"line":77,"column":1},"end":{"line":77,"column":1}},"children":[{"type":"tableCell","align":"left","position":{"start":{"line":77,"column":1},"end":{"line":77,"column":1}},"children":[{"type":"text","value":"SRTM","position":{"start":{"line":77,"column":1},"end":{"line":77,"column":1}},"key":"VMoCvXrJYz"}],"key":"b9OwkRXNk8"},{"type":"tableCell","align":"left","position":{"start":{"line":77,"column":1},"end":{"line":77,"column":1}},"children":[{"type":"text","value":"Shuttle Radar Topography Mission","position":{"start":{"line":77,"column":1},"end":{"line":77,"column":1}},"key":"eDBJJGgE5c"}],"key":"mNm7QroWvc"}],"key":"mWoMEbvy8a"},{"type":"tableRow","position":{"start":{"line":78,"column":1},"end":{"line":78,"column":1}},"children":[{"type":"tableCell","align":"left","position":{"start":{"line":78,"column":1},"end":{"line":78,"column":1}},"children":[{"type":"text","value":"ST","position":{"start":{"line":78,"column":1},"end":{"line":78,"column":1}},"key":"LcDr77GMBQ"}],"key":"nbh4bXTNg2"},{"type":"tableCell","align":"left","position":{"start":{"line":78,"column":1},"end":{"line":78,"column":1}},"children":[{"type":"text","value":"Science Team","position":{"start":{"line":78,"column":1},"end":{"line":78,"column":1}},"key":"KUDBI9yeyW"}],"key":"YbvHPZPVme"}],"key":"xRQ0LiMQLX"},{"type":"tableRow","position":{"start":{"line":79,"column":1},"end":{"line":79,"column":1}},"children":[{"type":"tableCell","align":"left","position":{"start":{"line":79,"column":1},"end":{"line":79,"column":1}},"children":[{"type":"text","value":"TAI","position":{"start":{"line":79,"column":1},"end":{"line":79,"column":1}},"key":"PuxfK5LNsB"}],"key":"YtHIfHzDbh"},{"type":"tableCell","align":"left","position":{"start":{"line":79,"column":1},"end":{"line":79,"column":1}},"children":[{"type":"text","value":"International Atomic Time (Temps Atomique International)","position":{"start":{"line":79,"column":1},"end":{"line":79,"column":1}},"key":"kKWLuAwVH9"}],"key":"p7Y1IV9a0T"}],"key":"YI53YRp0Al"},{"type":"tableRow","position":{"start":{"line":80,"column":1},"end":{"line":80,"column":1}},"children":[{"type":"tableCell","align":"left","position":{"start":{"line":80,"column":1},"end":{"line":80,"column":1}},"children":[{"type":"text","value":"TCF","position":{"start":{"line":80,"column":1},"end":{"line":80,"column":1}},"key":"WFEsIuLW2j"}],"key":"QJAK8G3XgL"},{"type":"tableCell","align":"left","position":{"start":{"line":80,"column":1},"end":{"line":80,"column":1}},"children":[{"type":"text","value":"Terrain Correction Factor","position":{"start":{"line":80,"column":1},"end":{"line":80,"column":1}},"key":"YPRdqWcLeE"}],"key":"RC0RDZN3TW"}],"key":"NIVQvaHrH7"},{"type":"tableRow","position":{"start":{"line":81,"column":1},"end":{"line":81,"column":1}},"children":[{"type":"tableCell","align":"left","position":{"start":{"line":81,"column":1},"end":{"line":81,"column":1}},"children":[{"type":"text","value":"TEC","position":{"start":{"line":81,"column":1},"end":{"line":81,"column":1}},"key":"lNeBXV3UQ2"}],"key":"OvO483WX4P"},{"type":"tableCell","align":"left","position":{"start":{"line":81,"column":1},"end":{"line":81,"column":1}},"children":[{"type":"text","value":"Total Electron Content","position":{"start":{"line":81,"column":1},"end":{"line":81,"column":1}},"key":"fiI1IUfc2J"}],"key":"PcN6LjgqoS"}],"key":"Qbx8cBACTu"},{"type":"tableRow","position":{"start":{"line":82,"column":1},"end":{"line":82,"column":1}},"children":[{"type":"tableCell","align":"left","position":{"start":{"line":82,"column":1},"end":{"line":82,"column":1}},"children":[{"type":"text","value":"TFdb","position":{"start":{"line":82,"column":1},"end":{"line":82,"column":1}},"key":"QUDvnLXCsc"}],"key":"WWRnbN9oSC"},{"type":"tableCell","align":"left","position":{"start":{"line":82,"column":1},"end":{"line":82,"column":1}},"children":[{"type":"text","value":"Track-frame Database","position":{"start":{"line":82,"column":1},"end":{"line":82,"column":1}},"key":"FHT5xgLFcd"}],"key":"KmHnNiAcD0"}],"key":"w4KRZGXzTU"},{"type":"tableRow","position":{"start":{"line":83,"column":1},"end":{"line":83,"column":1}},"children":[{"type":"tableCell","align":"left","position":{"start":{"line":83,"column":1},"end":{"line":83,"column":1}},"children":[{"type":"text","value":"SWST","position":{"start":{"line":83,"column":1},"end":{"line":83,"column":1}},"key":"NLbOdKXO6Q"}],"key":"rSDNgzUuF6"},{"type":"tableCell","align":"left","position":{"start":{"line":83,"column":1},"end":{"line":83,"column":1}},"children":[{"type":"text","value":"Sampling Window Start Time","position":{"start":{"line":83,"column":1},"end":{"line":83,"column":1}},"key":"IzijMl2hZ6"}],"key":"o6ASPxzEby"}],"key":"AUjGqLvKxj"},{"type":"tableRow","position":{"start":{"line":84,"column":1},"end":{"line":84,"column":1}},"children":[{"type":"tableCell","align":"left","position":{"start":{"line":84,"column":1},"end":{"line":84,"column":1}},"children":[{"type":"text","value":"UR","position":{"start":{"line":84,"column":1},"end":{"line":84,"column":1}},"key":"O7MrR9Y8dq"}],"key":"zwJP6xGkRO"},{"type":"tableCell","align":"left","position":{"start":{"line":84,"column":1},"end":{"line":84,"column":1}},"children":[{"type":"text","value":"Urgent Response","position":{"start":{"line":84,"column":1},"end":{"line":84,"column":1}},"key":"cCi8QvZ6P1"}],"key":"UcG22HjHaz"}],"key":"kRz7kuiojP"},{"type":"tableRow","position":{"start":{"line":85,"column":1},"end":{"line":85,"column":1}},"children":[{"type":"tableCell","align":"left","position":{"start":{"line":85,"column":1},"end":{"line":85,"column":1}},"children":[{"type":"text","value":"UTC","position":{"start":{"line":85,"column":1},"end":{"line":85,"column":1}},"key":"VAfZ9oMh4j"}],"key":"ICIz8YQaIM"},{"type":"tableCell","align":"left","position":{"start":{"line":85,"column":1},"end":{"line":85,"column":1}},"children":[{"type":"text","value":"Universal Time Coordinated","position":{"start":{"line":85,"column":1},"end":{"line":85,"column":1}},"key":"oezsdCM3nJ"}],"key":"ECh66JPGim"}],"key":"noaY4sHedV"},{"type":"tableRow","position":{"start":{"line":86,"column":1},"end":{"line":86,"column":1}},"children":[{"type":"tableCell","align":"left","position":{"start":{"line":86,"column":1},"end":{"line":86,"column":1}},"children":[{"type":"abbreviation","title":"Universal Transverse Mercator","children":[{"type":"text","value":"UTM","key":"Jm3imFsuOn"}],"key":"sCaQTufHP8"}],"key":"WTznOBXYB3"},{"type":"tableCell","align":"left","position":{"start":{"line":86,"column":1},"end":{"line":86,"column":1}},"children":[{"type":"text","value":"Universal Transverse Mercator","position":{"start":{"line":86,"column":1},"end":{"line":86,"column":1}},"key":"mSia6lTDv5"}],"key":"i0uHOCLrd7"}],"key":"xdXzWdaCuD"},{"type":"tableRow","position":{"start":{"line":87,"column":1},"end":{"line":87,"column":1}},"children":[{"type":"tableCell","align":"left","position":{"start":{"line":87,"column":1},"end":{"line":87,"column":1}},"children":[{"type":"text","value":"WGS84","position":{"start":{"line":87,"column":1},"end":{"line":87,"column":1}},"key":"dwiJwFHwA6"}],"key":"igAACmKTns"},{"type":"tableCell","align":"left","position":{"start":{"line":87,"column":1},"end":{"line":87,"column":1}},"children":[{"type":"text","value":"World Geodetic System 84","position":{"start":{"line":87,"column":1},"end":{"line":87,"column":1}},"key":"DgmzUGTHgC"}],"key":"GIAeKCdoig"}],"key":"xwZqEXq9rt"},{"type":"tableRow","position":{"start":{"line":88,"column":1},"end":{"line":88,"column":1}},"children":[{"type":"tableCell","align":"left","position":{"start":{"line":88,"column":1},"end":{"line":88,"column":1}},"children":[{"type":"text","value":"XML","position":{"start":{"line":88,"column":1},"end":{"line":88,"column":1}},"key":"VVcL3VZink"}],"key":"GFY5e8SjtG"},{"type":"tableCell","align":"left","position":{"start":{"line":88,"column":1},"end":{"line":88,"column":1}},"children":[{"type":"text","value":"eXtensible Markup Language (xml in code)","position":{"start":{"line":88,"column":1},"end":{"line":88,"column":1}},"key":"HUJUF4ns3K"}],"key":"MbmDCDjrsG"}],"key":"LI9ZNpN0S4"},{"type":"tableRow","position":{"start":{"line":89,"column":1},"end":{"line":89,"column":1}},"children":[{"type":"tableCell","align":"left","position":{"start":{"line":89,"column":1},"end":{"line":89,"column":1}},"children":[{"type":"text","value":"YAML","position":{"start":{"line":89,"column":1},"end":{"line":89,"column":1}},"key":"y2wABjicZe"}],"key":"FT03MYvEwX"},{"type":"tableCell","align":"left","position":{"start":{"line":89,"column":1},"end":{"line":89,"column":1}},"children":[{"type":"text","value":"YAML Aint Markup Language","position":{"start":{"line":89,"column":1},"end":{"line":89,"column":1}},"key":"FqyeldonuU"}],"key":"K3SNP18jsS"}],"key":"HVPp3Te57u"}],"key":"ujeMgi8UsB"}],"key":"nWuaYvu8p6"}],"key":"jYLEG0z0sD"},"references":{"cite":{"order":[],"data":{}}}}