{"version":3,"kind":"Article","sha256":"f7040ebf838b6ae1113bbcfa14f81f0e40119a223be6e00dff5ecd39cba089a9","slug":"earthdata-forum","location":"/user-support/earthdata-forum.md","dependencies":[],"frontmatter":{"title":"Earthdata Forum","content_includes_title":false,"github":"https://github.com/ua-asf/nisar-docs","numbering":{"figure":{"enabled":true,"continue":true},"title":{"offset":1}},"abbreviations":{"AWS":"Amazon Web Services","DAAC":"Distributed Active Archive Center","DEM":"Digital Elevation Model","EDC":"Earthdata Cloud","ESDIS":"Earth Science Data and Information System","GCOV":"Geocoded Polarimetric Covariance","GOFF":"Geocoded Pixel Offsets","GSLC":"Geocoded Single Look Complex","GUNW":"Geocoded Unwrapped Interferogram","NISAR":"NASA-ISRO Synthetic Aperture Radar","NRB":"Normalized Radar Backscatter","RTC":"Radiometric Terrain Correction; Radiometrically Terrain-Corrected","SAR":"Synthetic Aperture Radar","UTM":"Universal Transverse Mercator","RIFG":"Range Doppler Wrapped Interferogram","ROFF":"Range Doppler Pixel Offsets","RRSD":"Radar Raw Signal Data","RSLC":"Range Doppler Single Look Complex","RUNW":"Range Doppler Unwrapped Interferogram"},"source_url":"https://github.com/ua-asf/nisar-docs/blob/s3-access/user-support/earthdata-forum.md","edit_url":"https://github.com/ua-asf/nisar-docs/edit/s3-access/user-support/earthdata-forum.md","exports":[{"format":"md","filename":"earthdata-forum.md","url":"/nisar-docs-preview/8/build/earthdata-forum-73cbdf04a9ebfdb93cdeb50f7d996040.md"}]},"mdast":{"type":"root","children":[{"type":"block","children":[{"type":"paragraph","position":{"start":{"line":3,"column":1},"end":{"line":3,"column":1}},"children":[{"type":"text","value":"The ","position":{"start":{"line":3,"column":1},"end":{"line":3,"column":1}},"key":"K1QvXZvAZM"},{"type":"link","url":"https://forum.earthdata.nasa.gov/","position":{"start":{"line":3,"column":1},"end":{"line":3,"column":1}},"children":[{"type":"text","value":"Earthdata Forum","position":{"start":{"line":3,"column":1},"end":{"line":3,"column":1}},"key":"YdGbfmnUsY"}],"urlSource":"https://forum.earthdata.nasa.gov/","key":"LfkT75trhz"},{"type":"text","value":" is the means of choice for communication on topics involving NASA Earth Science data. Subject matter experts answer questions approved by the moderators. Tags for the following categories are assigned to all topics in the forum: ","position":{"start":{"line":3,"column":1},"end":{"line":3,"column":1}},"key":"gA2FpPdRcv"},{"type":"emphasis","position":{"start":{"line":3,"column":1},"end":{"line":3,"column":1}},"children":[{"type":"text","value":"Discipline","position":{"start":{"line":3,"column":1},"end":{"line":3,"column":1}},"key":"FtZg7CZ5iE"}],"key":"DDuemeOygn"},{"type":"text","value":", ","position":{"start":{"line":3,"column":1},"end":{"line":3,"column":1}},"key":"UOeiI6N9Qw"},{"type":"emphasis","position":{"start":{"line":3,"column":1},"end":{"line":3,"column":1}},"children":[{"type":"abbreviation","title":"Distributed Active Archive Center","children":[{"type":"text","value":"DAAC","key":"fFmjx6KIpp"}],"key":"jCIGtt3K0W"}],"key":"A8GpgVATwz"},{"type":"text","value":", ","position":{"start":{"line":3,"column":1},"end":{"line":3,"column":1}},"key":"NzWa7Zyc4y"},{"type":"emphasis","position":{"start":{"line":3,"column":1},"end":{"line":3,"column":1}},"children":[{"type":"text","value":"Project","position":{"start":{"line":3,"column":1},"end":{"line":3,"column":1}},"key":"yM94WX5YnP"}],"key":"qFFhvYaXQm"},{"type":"text","value":", and ","position":{"start":{"line":3,"column":1},"end":{"line":3,"column":1}},"key":"Pvs573wth9"},{"type":"emphasis","position":{"start":{"line":3,"column":1},"end":{"line":3,"column":1}},"children":[{"type":"text","value":"Services/Usage","position":{"start":{"line":3,"column":1},"end":{"line":3,"column":1}},"key":"nq5JKM78uf"}],"key":"mD64HPOPHs"},{"type":"text","value":". These tags can be used to filter the topics, and tags specific to the ","key":"gPqXWckxPn"},{"type":"abbreviation","title":"NASA-ISRO Synthetic Aperture Radar","children":[{"type":"text","value":"NISAR","key":"eIw2Lc5eyj"}],"key":"Xf4HkPTOw9"},{"type":"text","value":" mission have been added. Users will want to pay particular attention to ","key":"QCVXep9vbX"},{"type":"emphasis","position":{"start":{"line":3,"column":1},"end":{"line":3,"column":1}},"children":[{"type":"text","value":"ASF","position":{"start":{"line":3,"column":1},"end":{"line":3,"column":1}},"key":"um1Zl8rxgK"}],"key":"GyT7ml1FHX"},{"type":"text","value":" posts tagged with ","position":{"start":{"line":3,"column":1},"end":{"line":3,"column":1}},"key":"WcBNlZkZil"},{"type":"emphasis","position":{"start":{"line":3,"column":1},"end":{"line":3,"column":1}},"children":[{"type":"text","value":"Announcements","position":{"start":{"line":3,"column":1},"end":{"line":3,"column":1}},"key":"ir4OWs9xBO"}],"key":"xxil9HH1K8"},{"type":"text","value":", ","position":{"start":{"line":3,"column":1},"end":{"line":3,"column":1}},"key":"ocSWeC38t2"},{"type":"emphasis","position":{"start":{"line":3,"column":1},"end":{"line":3,"column":1}},"children":[{"type":"text","value":"Data Recipes","position":{"start":{"line":3,"column":1},"end":{"line":3,"column":1}},"key":"DyZm7nfUiF"}],"key":"sSyR7wXU8q"},{"type":"text","value":", and ","position":{"start":{"line":3,"column":1},"end":{"line":3,"column":1}},"key":"iOx5A1U0lV"},{"type":"emphasis","position":{"start":{"line":3,"column":1},"end":{"line":3,"column":1}},"children":[{"type":"text","value":"FAQ","position":{"start":{"line":3,"column":1},"end":{"line":3,"column":1}},"key":"aPn4pAuVCL"}],"key":"AV2oxT5vnB"},{"type":"text","value":".","position":{"start":{"line":3,"column":1},"end":{"line":3,"column":1}},"key":"grIgrF6izf"}],"key":"PHTx55Pd9E"},{"type":"paragraph","position":{"start":{"line":5,"column":1},"end":{"line":5,"column":1}},"children":[{"type":"text","value":"Users can also contact ASF directly by emailing ","position":{"start":{"line":5,"column":1},"end":{"line":5,"column":1}},"key":"aCF5jPtuEA"},{"type":"link","url":"mailto:uso@asf.alaska.edu","position":{"start":{"line":5,"column":1},"end":{"line":5,"column":1}},"children":[{"type":"text","value":"uso@asf.alaska.edu","position":{"start":{"line":5,"column":1},"end":{"line":5,"column":1}},"key":"KuXhICCqNu"}],"urlSource":"mailto:uso@asf.alaska.edu","key":"ygCOJopmGq"},{"type":"text","value":".","position":{"start":{"line":5,"column":1},"end":{"line":5,"column":1}},"key":"nbulQzuVLp"}],"key":"pBqEV3j1Au"}],"key":"kIjZ3svcGk"}],"key":"MubpU0WCi6"},"references":{"cite":{"order":[],"data":{}}},"footer":{"navigation":{"prev":{"title":"White Papers and Documents","url":"/documents","group":"User Support"},"next":{"title":"Acronyms","url":"/acronyms","group":"Appendices"}}},"domain":"http://localhost:3000"}